filesify/__init__.py
filesify/admin.py
filesify/apps.py
filesify/mixins.py
filesify/models.py
filesify/__pycache__/__init__.cpython-310.pyc
filesify/__pycache__/__init__.cpython-311.pyc
filesify/__pycache__/admin.cpython-310.pyc
filesify/__pycache__/apps.cpython-310.pyc
filesify/__pycache__/mixins.cpython-310.pyc
filesify/__pycache__/models.cpython-310.pyc
filesify/management/commands/create_files.py
filesify/tests/models.py
filesify/tests/runtests.py
filesify/tests/settings.py
filesify/tests/tests.py
filesify/tests/__pycache__/runtests.cpython-310-pytest-6.2.5.pyc
filesify/tests/__pycache__/settings.cpython-310.pyc
filesify/tests/__pycache__/test_models.cpython-310-pytest-6.2.5.pyc
filesify/tests/__pycache__/tests.cpython-310.pyc
filesify/tests/__pycache__/tests_models.cpython-310-pytest-6.2.5.pyc
django_filesify-0.1.dist-info/AUTHORS
django_filesify-0.1.dist-info/LICENSE
django_filesify-0.1.dist-info/METADATA
django_filesify-0.1.dist-info/WHEEL
django_filesify-0.1.dist-info/top_level.txt
django_filesify-0.1.dist-info/RECORD
