Metadata-Version: 2.1
Name: django-filesify
Version: 0.1
Summary: A Django reusable app to create physical files from database text field.
Home-page: https://github.com/lazybird/django-filesify/
Author: 
Author-email: 
Keywords: filesify django files container upload configuration volatile storage
License-File: LICENSE
License-File: AUTHORS
